{
  "name": "단고을",
  "nameEn": "DANGOEUL",
  "tagline": "지역 농산물 직거래",
  "tel": "010-9599-4561",
  "email": "hello@dangoeul.kr",
  "address": "충청북도 진천군 이월면 노원리 360번지",
  "seo": {
    "siteUrl": "https://www.dangoeul.kr",
    "title": "단고을 DANGOEUL — 지역 농산물 직거래 · 진천 모종 육묘",
    "description": "밭에서 식탁까지 신선한 지역 농산물 직거래. 충북 진천 모종 육묘 하우스, 채소 모종·제철 박스·새벽 배송·농장 픽업. 직거래 안내·문의·주문.",
    "keywords": "단고을,DANGOEUL,진천,모종,육묘,채소 모종,비닐하우스,농산물 직거래,새벽 배송,제철,쌈채소,상추 모종,깻잎 모종,지역 농산물",
    "ogImagePath": "assets/images/brand-dangoeul-logo.png",
    "locale": "ko_KR",
    "naverSiteVerification": "",
    "googleSiteVerification": ""
  },
  "brandLogo": "assets/images/brand-dangoeul-logo.png",
  "facility": {
    "hero": "assets/images/facility/interior-scale-wide.png",
    "productsBanner": "assets/images/facility/interior-benches-blue.png",
    "gallery": [
      {
        "src": "assets/images/facility/exterior-greenhouse.png",
        "caption": "모종 육묘 비닐하우스 전경"
      },
      {
        "src": "assets/images/facility/interior-benches-blue.png",
        "caption": "육묘대·파종 트레이 라인"
      },
      {
        "src": "assets/images/facility/interior-rows-perspective.png",
        "caption": "하우스 내부 — 다양한 모종 동시 육묘"
      },
      {
        "src": "assets/images/facility/interior-hoop-long.png",
        "caption": "아치형 온실 — 일사·환기 설계"
      },
      {
        "src": "assets/images/facility/interior-scale-wide.png",
        "caption": "대규모 육묘 시설"
      },
      {
        "src": "assets/images/facility/interior-sprouts-trays.png",
        "caption": "플러그 트레이 대량 출하 준비"
      }
    ]
  },
  "homeSections": [
    {
      "key": "weekly",
      "title": "이번 주 추천 모종",
      "subtitle": "온실 출고 기준 · 한정 수량",
      "productIds": [
        1,
        2,
        3
      ]
    },
    {
      "key": "best",
      "title": "베스트 상품",
      "subtitle": "재구매·문의가 많은 모종·세트",
      "productIds": [
        1,
        8,
        10
      ]
    },
    {
      "key": "new",
      "title": "새로 나온 상품",
      "subtitle": "이번 시즌 입고·신규 라인",
      "productIds": [
        12,
        14,
        15
      ]
    }
  ],
  "topMenu": [
    {
      "id": "home",
      "label": "홈",
      "icon": "🏠"
    },
    {
      "id": "about",
      "label": "브랜드",
      "icon": "🌾"
    },
    {
      "id": "solution",
      "label": "직거래 안내",
      "icon": "📦"
    },
    {
      "id": "products",
      "label": "제철 상품",
      "icon": "🥬"
    },
    {
      "id": "detail",
      "label": "상품 상세",
      "icon": "🔍"
    },
    {
      "id": "blog",
      "label": "소식·레시피",
      "icon": "📝"
    },
    {
      "id": "location",
      "label": "오시는 길",
      "icon": "📍"
    },
    {
      "id": "contact",
      "label": "문의·주문",
      "icon": "📞"
    },
    {
      "id": "order",
      "label": "주문하기",
      "icon": "🧾"
    },
    {
      "id": "faq",
      "label": "FAQ",
      "icon": "❓"
    }
  ],
  "sidebarMenu": [
    {
      "section": "직거래",
      "items": [
        {
          "id": "home",
          "label": "홈",
          "icon": "🏠"
        },
        {
          "id": "solution",
          "label": "직거래 안내",
          "icon": "📦"
        },
        {
          "id": "products",
          "label": "제철 상품",
          "icon": "🥬"
        }
      ]
    },
    {
      "section": "단고을",
      "items": [
        {
          "id": "about",
          "label": "브랜드",
          "icon": "🌾"
        },
        {
          "id": "blog",
          "label": "소식·레시피",
          "icon": "📝"
        }
      ]
    },
    {
      "section": "고객지원",
      "items": [
        {
          "id": "location",
          "label": "오시는 길",
          "icon": "📍"
        },
        {
          "id": "contact",
          "label": "문의·주문",
          "icon": "📞"
        },
        {
          "id": "order",
          "label": "주문하기",
          "icon": "🧾"
        },
        {
          "id": "faq",
          "label": "FAQ",
          "icon": "❓"
        }
      ]
    }
  ],
  "solutions": [
    {
      "id": 1,
      "emoji": "🚚",
      "title": "새벽 배송",
      "desc": "수확 당일 포장해 새벽 시간대에 도착하는 콜드체인 배송.",
      "tags": [
        "배송",
        "신선도"
      ],
      "badge": "인기"
    },
    {
      "id": 2,
      "emoji": "📅",
      "title": "정기 구독 박스",
      "desc": "제철 농산물을 매주·격주로 큐레이션해 보내드립니다.",
      "tags": [
        "구독",
        "제철"
      ],
      "badge": "NEW"
    },
    {
      "id": 3,
      "emoji": "🏡",
      "title": "농장 픽업",
      "desc": "현장 방문 후 직접 수령 — 당일 수확 상품을 만나보세요.",
      "tags": [
        "픽업",
        "체험"
      ],
      "badge": ""
    },
    {
      "id": 4,
      "emoji": "🤝",
      "title": "지역 협동조합 연계",
      "desc": "인근 농가와 함께하는 공동 출하·품질 관리.",
      "tags": [
        "로컬",
        "공동출하"
      ],
      "badge": ""
    },
    {
      "id": 5,
      "emoji": "📷",
      "title": "생산 과정 공개",
      "desc": "재배·가공 과정을 사진·영상으로 투명하게 안내합니다.",
      "tags": [
        "신뢰",
        "스토리"
      ],
      "badge": ""
    },
    {
      "id": 6,
      "emoji": "♻️",
      "title": "친환경 포장",
      "desc": "재활용 가능한 포장재와 최소 비닐 사용을 지향합니다.",
      "tags": [
        "친환경",
        "ESG"
      ],
      "badge": ""
    }
  ],
  "products": [
    {
      "id": 1,
      "emoji": "🥬",
      "name": "[단고을] 싱싱한 적상추 모종 (1포트)",
      "category": "모종",
      "desc": "뿌리 뭉치가 하얗고 튼튼한 적상추 모종. 비닐하우스 트레이 배경 그대로 — 이식 후 활착에 유리합니다.",
      "price": "1,200원",
      "demo": "https://demo.dangoeul.kr/p01",
      "image": "assets/images/products/p01-jeoksangchu-root.png"
    },
    {
      "id": 2,
      "emoji": "🌿",
      "name": "적상추 모종 (붉은 잎)",
      "category": "모종",
      "desc": "적갈색 잎맥이 선명한 적상추. 물방울 맺힌 신선 잎 — 샐러드·쌈용.",
      "price": "1,200원",
      "demo": "https://demo.dangoeul.kr/p02",
      "image": "assets/images/products/p02-red-lettuce-hand.png"
    },
    {
      "id": 3,
      "emoji": "🍃",
      "name": "깻잎 모종 (밀생육)",
      "category": "모종",
      "desc": "하트형 잎이 빽빽한 육묘 단지. 향 좋은 깻잎 — 쌈채소 대표 품목.",
      "price": "1,000원",
      "demo": "https://demo.dangoeul.kr/p03",
      "image": "assets/images/products/p03-kkaennip-dense.png"
    },
    {
      "id": 4,
      "emoji": "🥦",
      "name": "브라시카 모종 트레이 (케일·배추류)",
      "category": "모종",
      "desc": "검은 플러그 트레이에 고르게 올라온 아삭한 묘. 브로콜리·케일·배추 묘 재배.",
      "price": "판별 문의",
      "demo": "https://demo.dangoeul.kr/p04",
      "image": "assets/images/products/p04-brassica-trays.png"
    },
    {
      "id": 5,
      "emoji": "🌱",
      "name": "청상추·청경채 계열 모종 (밀집)",
      "category": "모종",
      "desc": "잎 끝에 물방울 맺힌 싱싱한 연녹색 묘. 샐러드·볶음배추 심기 좋은 시기.",
      "price": "1,100원",
      "demo": "https://demo.dangoeul.kr/p05",
      "image": "assets/images/products/p05-lettuce-sea.png"
    },
    {
      "id": 6,
      "emoji": "🥗",
      "name": "버터헤드 상추 트레이 (육묘판)",
      "category": "모종",
      "desc": "로제트가 고른 버터헤드형. 트레이 전체가 한 격자 패턴 — 덩어리 주문 시 협의.",
      "price": "판별 문의",
      "demo": "https://demo.dangoeul.kr/p06",
      "image": "assets/images/products/p06-butterhead-tray.png"
    },
    {
      "id": 7,
      "emoji": "💚",
      "name": "상추 모종 (손바닥 비교)",
      "category": "모종",
      "desc": "손에 올려 크기 확인 가능한 개별 묘. 포트에서 막 뽑은 듯한 로제트.",
      "price": "1,100원",
      "demo": "https://demo.dangoeul.kr/p07",
      "image": "assets/images/products/p07-lettuce-hand-palm.png"
    },
    {
      "id": 8,
      "emoji": "✨",
      "name": "버터헤드 상추 (뿌리 발달)",
      "category": "모종",
      "desc": "흰 뿌리가 포트를 감싼 프리미엄 묘. “뿌리가 생명” — 이식 직후 생존률 강조.",
      "price": "1,300원",
      "demo": "https://demo.dangoeul.kr/p08",
      "image": "assets/images/products/p08-butterhead-roots.png"
    },
    {
      "id": 9,
      "emoji": "🍃",
      "name": "깻잎 모종 (플러그)",
      "category": "모종",
      "desc": "깻잎 특유의 잎 모양·거친 잎결. 원통형 플러그에 실뿌리 밀착.",
      "price": "1,000원",
      "demo": "https://demo.dangoeul.kr/p09",
      "image": "assets/images/products/p09-kkaennip-plug.png"
    },
    {
      "id": 10,
      "emoji": "🍅",
      "name": "방울토마토 모종",
      "category": "모종",
      "desc": "복엽·털이 도드라진 토마토 묘. 줄기 튼튼 — 베란다·하우스 재배용.",
      "price": "1,500원",
      "demo": "https://demo.dangoeul.kr/p10",
      "image": "assets/images/products/p10-tomato-seedling.png"
    },
    {
      "id": 11,
      "emoji": "🥦",
      "name": "브로콜리 모종 (1포)",
      "category": "모종",
      "desc": "분무 녹 잎의 브라시카 묘. 배경 트레이와 동일 품질로 출고.",
      "price": "1,200원",
      "demo": "https://demo.dangoeul.kr/p11",
      "image": "assets/images/products/p11-broccoli-hand.png"
    },
    {
      "id": 12,
      "emoji": "🟣",
      "name": "적 겨자 모종 (보라 잎맥)",
      "category": "모종",
      "desc": "적색 맥이 도드라진 겨자류. 샐러드·감칠맛 — 트레이 단위 구매 가능.",
      "price": "1,200원",
      "demo": "https://demo.dangoeul.kr/p12",
      "image": "assets/images/products/p12-red-mustard.png"
    },
    {
      "id": 13,
      "emoji": "🏡",
      "name": "깻잎 모종 (하우스 대단지)",
      "category": "모종",
      "desc": "진천 온실에서 키운 깻잎 묘 대면적 컷. 대량·도매 문의 환영.",
      "price": "판별 문의",
      "demo": "https://demo.dangoeul.kr/p13",
      "image": "assets/images/products/p13-kkaennip-greenhouse.png"
    },
    {
      "id": 14,
      "emoji": "🥬",
      "name": "배추·양배추 모종 (플러그)",
      "category": "모종",
      "desc": "넓은 원형 잎의 배추류 묘. 김장·봄 배추 심기 적합.",
      "price": "1,000원",
      "demo": "https://demo.dangoeul.kr/p14",
      "image": "assets/images/products/p14-cabbage-hand.png"
    },
    {
      "id": 15,
      "emoji": "🍅",
      "name": "토마토 모종 (대단지·손 비교)",
      "category": "모종",
      "desc": "수만 주 묘 중 한 포를 들어 올린 컷. 대규모 육묘와 개체 품질을 함께 확인.",
      "price": "1,500원",
      "demo": "https://demo.dangoeul.kr/p15",
      "image": "assets/images/products/p15-tomato-field-hand.png"
    },
    {
      "id": 16,
      "emoji": "🎁",
      "name": "[실속세트] 적상추 모종 10포 / 20포",
      "category": "세트",
      "desc": "주력 적상추를 수량별로 묶은 실속 구성. 가정·소규모 텃밭용.",
      "price": "10포 9,500원 / 20포 17,500원",
      "demo": "https://demo.dangoeul.kr/set10",
      "image": "assets/images/products/p01-jeoksangchu-root.png",
      "isSet": true,
      "setItems": [
        "적상추 모종 1포트 × 10 또는 × 20",
        "심기 순서 안내지",
        "포장 시 뿌리·잎 상태 검수"
      ]
    },
    {
      "id": 17,
      "emoji": "🎁",
      "name": "[주말농장] 쌈채소 모둠 세트",
      "category": "세트",
      "desc": "깻잎·상추·(시즌) 고추 묘 등 쌈 라인을 한 번에. 사진은 하우스 깻잎 육묘 현장.",
      "price": "세트 28,000원~",
      "demo": "https://demo.dangoeul.kr/set-ssam",
      "image": "assets/images/products/p13-kkaennip-greenhouse.png",
      "isSet": true,
      "setItems": [
        "깻잎 모종",
        "청·적상추 모종",
        "시즌 고추 묘(재고)",
        "배송 전 물주기·포장"
      ]
    },
    {
      "id": 18,
      "emoji": "🎁",
      "name": "텃밭 스타터 세트 (잎채소+토마토)",
      "category": "세트",
      "desc": "잎채소와 토마토 묘를 조합한 입문 세트. 베란다·작은 텃밭에 맞춤.",
      "price": "세트 32,000원~",
      "demo": "https://demo.dangoeul.kr/set-starter",
      "image": "assets/images/products/p08-butterhead-roots.png",
      "isSet": true,
      "setItems": [
        "버터헤드 상추 묘",
        "방울토마토 묘",
        "배양토 소포장(선택)",
        "이식 요령 카드"
      ]
    }
  ],
  "faqs": [
    {
      "q": "배송은 며칠 걸리나요?",
      "a": "주문 마감(전일 18시) 후 새벽 배송 기준 익일 도착입니다. 도서·산간은 1~2일 추가될 수 있습니다."
    },
    {
      "q": "농약은 어떻게 관리하나요?",
      "a": "잔류 농약 검사 리포트를 분기별로 공개하며, 가능한 저농약·유기농 재배를 우선합니다."
    },
    {
      "q": "정기 구독은 중단할 수 있나요?",
      "a": "마이페이지 또는 고객센터에서 언제든 휴회·해지 가능합니다. 위약금은 없습니다."
    },
    {
      "q": "단체·기업 주문이 가능한가요?",
      "a": "네. 문의·주문 메뉴에서 수량과 납품일을 남겨주시면 견적을 드립니다."
    },
    {
      "q": "불만족 시 환불은?",
      "a": "수령 후 24시간 이내 사진 첨부 시 신선도 기준에 따라 전액 또는 부분 환불을 도와드립니다."
    }
  ],
  "codes": [
    { "code_id": 1, "code_grp": "dangoeul_contact_service", "code_value": "새벽 배송", "code_label": "새벽 배송" },
    { "code_id": 2, "code_grp": "dangoeul_contact_service", "code_value": "정기 구독 박스", "code_label": "정기 구독 박스" },
    { "code_id": 3, "code_grp": "dangoeul_contact_service", "code_value": "농장 픽업", "code_label": "농장 픽업" },
    { "code_id": 4, "code_grp": "dangoeul_contact_service", "code_value": "지역 협동조합 연계", "code_label": "지역 협동조합 연계" },
    { "code_id": 5, "code_grp": "dangoeul_contact_service", "code_value": "생산 과정 공개", "code_label": "생산 과정 공개" },
    { "code_id": 6, "code_grp": "dangoeul_contact_service", "code_value": "친환경 포장", "code_label": "친환경 포장" },
    { "code_id": 7, "code_grp": "dangoeul_contact_service", "code_value": "기타 문의", "code_label": "기타 문의" }
  ]
}